pytest_pyvista/__init__.py
pytest_pyvista/doc_mode.py
pytest_pyvista/hooks.py
pytest_pyvista/pytest_pyvista.py
pytest_pyvista-0.3.1.dist-info/entry_points.txt
pytest_pyvista-0.3.1.dist-info/licenses/LICENSE
pytest_pyvista-0.3.1.dist-info/WHEEL
pytest_pyvista-0.3.1.dist-info/METADATA
pytest_pyvista-0.3.1.dist-info/RECORD
