Metadata-Version: 2.4
Name: pytest_pyvista
Version: 0.3.1
Summary: Pytest-pyvista package.
Author-email: The PyVista developers <info@pyvista.org>
License-Expression: MIT
Classifier: Development Status :: 4 - Beta
Classifier: Framework :: Pytest
Classifier: Intended Audience :: Developers
Classifier: Operating System :: OS Independent
Classifier: Programming Language :: Python :: 3.10
Classifier: Programming Language :: Python :: 3.11
Classifier: Programming Language :: Python :: 3.12
Classifier: Programming Language :: Python :: 3.13
Classifier: Topic :: Software Development :: Testing
License-File: LICENSE
Requires-Dist: pytest>=6.2.0
Requires-Dist: pydata-sphinx-theme==0.16.1 ; extra == "docs"
Requires-Dist: sphinx-notfound-page==1.1.0 ; extra == "docs"
Requires-Dist: sphinx==8.2.1 ; extra == "docs"
Requires-Dist: sphinx_copybutton==0.5.2 ; extra == "docs"
Requires-Dist: codecov<2.2.0 ; extra == "tests"
Requires-Dist: coverage==7.10.7 ; extra == "tests"
Requires-Dist: numpy<2.3 ; extra == "tests"
Requires-Dist: pytest-cov==7.0.0 ; extra == "tests"
Requires-Dist: pytest-pyvista[vtksz] ; extra == "tests"
Requires-Dist: pytest-xdist==3.8.0 ; extra == "tests"
Requires-Dist: pytest>=6.2.0 ; extra == "tests"
Requires-Dist: pytest_mock<3.16 ; extra == "tests"
Requires-Dist: pyvista[jupyter]>=0.37 ; extra == "tests"
Requires-Dist: playwright<1.56 ; extra == "vtksz"
Requires-Dist: trame-vtk<2.10 ; extra == "vtksz"
Requires-Dist: trame-vtk>=2.6 ; extra == "vtksz"
Project-URL: Home, https://github.com/pyvista/pytest-pyvista
Provides-Extra: docs
Provides-Extra: tests
Provides-Extra: vtksz
